patio/__init__.py
patio/broker/__init__.py
patio/broker/abc.py
patio/broker/memory.py
patio/broker/serializer.py
patio/broker/tcp/__init__.py
patio/broker/tcp/broker.py
patio/broker/tcp/protocol.py
patio/compat.py
patio/executor/__init__.py
patio/executor/asyncronous.py
patio/executor/base.py
patio/executor/null.py
patio/executor/process_pool.py
patio/executor/thread_pool.py
patio/py.typed
patio/registry.py
patio-0.1.4.dist-info/COPYING
patio-0.1.4.dist-info/METADATA
patio-0.1.4.dist-info/WHEEL
patio-0.1.4.dist-info/RECORD
